matpopmod/VERSION
matpopmod/__init__.py
matpopmod/collapsing.py
matpopmod/compadre.py
matpopmod/examples.py
matpopmod/ibm.py
matpopmod/kinship.py
matpopmod/mathtools.py
matpopmod/model.py
matpopmod/plot.py
matpopmod/random.py
matpopmod/trajectories.py
matpopmod/utils.py
matpopmod-0.1.1.dist-info/LICENSE
matpopmod-0.1.1.dist-info/METADATA
matpopmod-0.1.1.dist-info/WHEEL
matpopmod-0.1.1.dist-info/top_level.txt
matpopmod-0.1.1.dist-info/RECORD
