Metadata-Version: 2.1
Name: matpopmod
Version: 0.1.1
Summary: Matrix population models library with an interface to the COMPADRE / COMADRE databases.
Home-page: https://gitlab.com/bienvenu/matpopmod
Author: François Bienvenu et al.
Author-email: matpopmod@framalistes.org
License: LGPLv3+
Keywords: ecology demography populations compadre comadre
Platform: UNKNOWN
Classifier: Programming Language :: Python :: 3
Classifier: Operating System :: OS Independent
Classifier: Intended Audience :: Science/Research
Classifier: Topic :: Scientific/Engineering :: Bio-Informatics
Classifier: License :: OSI Approved :: GNU Lesser General Public License v3 or later (LGPLv3+)
Requires-Python: >=3
License-File: LICENSE
Requires-Dist: numpy
Requires-Dist: matplotlib
